exercise/model/mux_8to1.vhdl
library IEEE;
use IEEE.STD_LOGIC_1164.all;
---------------------
entity mux_8to1 is
 port(
     A,B,C,D,E,F,G,H : in STD_LOGIC_VECTOR(0 TO 1);
     S: in STD_LOGIC_VECTOR(0 To 2);
     ALU_RESULT: out STD_LOGIC_VECTOR(0 TO 1)
  );
end mux_8to1;
---------------------
architecture bhv of mux_8to1 is
begin
process (A,B,C,D,E,F,G,H, S) is
begin
  if (S(0) ='0' and S(1) = '0' and S(2) ='0') then
      ALU_RESULT <= A;
  elsif (S(0) ='0' and S(1) = '0' and S(2) ='1') then
      ALU_RESULT <= B;
  elsif (S(0) ='0' and S(1) = '1' and S(2) ='0') then
      ALU_RESULT <= C;
  elsif (S(0) ='0' and S(1) = '1' and S(2) ='1') then
      ALU_RESULT <= D;
  elsif (S(0) ='1' and S(1) = '0' and S(2) ='0') then
      ALU_RESULT <= E;
  elsif (S(0) ='1' and S(1) = '0' and S(2) ='1') then
      ALU_RESULT <= F;
  elsif (S(0) ='1' and S(1) = '1' and S(2) ='0') then
      ALU_RESULT <= G;
  else
      ALU_RESULT <= H;
  end if;

end process;
end bhv;

exercise/runme/fa.vhdl
LIBRARY IEEE;
USE IEEE.STD_LOGIC_1164.ALL;
 
ENTITY full_adder is
   PORT ( a : IN STD_LOGIC;
      b : IN STD_LOGIC;
      CarryIn : IN STD_LOGIC;
      Sum : OUT STD_LOGIC;
      CarryOut : OUT STD_LOGIC);
END full_adder;
 
ARCHITECTURE behavioral OF full_adder IS
 
BEGIN
 Sum <= A XOR B XOR CarryIn ;
 CarryOut <= (A AND B) OR (CarryIn AND A) 
               OR (CarryIn AND B) ;
end behavioral;

exercise/model/fa_2bit.vhdl
LIBRARY ieee;
USE ieee.std_logic_1164.all;
USE ieee.numeric_std.all;
---------------------------------
ENTITY full_adder_2bit IS
   PORT (A, B: IN STD_LOGIC_VECTOR(0 TO 1);
   RESULT:OUT STD_LOGIC_VECTOR(0 TO 1);
   CARRY_OUT: OUT STD_LOGIC);
END full_adder_2bit;
--------------------------------
ARCHITECTURE struct OF full_adder_2bit IS
   COMPONENT full_adder IS
      PORT (a, b, carryIn: IN STD_LOGIC;
      sum, carryOut: OUT STD_LOGIC);
   END COMPONENT;

   SIGNAL carryOut1: STD_LOGIC;
   SIGNAL noInput: STD_LOGIC := '0';
BEGIN
    full_adder2: full_adder port map(A(1), B(1), noInput, RESULT(1), carryOut1);
    full_adder1: full_adder port map(A(0), B(0), carryOut1, RESULT(0), CARRY_OUT);
END struct;

exercise/runme/not_gate.vhdl
LIBRARY ieee;
USE ieee.std_logic_1164.all;
---------------------------------
ENTITY not_gate IS
   PORT (A: IN STD_LOGIC_VECTOR(0 TO 1);
   B: OUT STD_LOGIC_VECTOR(0 TO 1));
END not_gate;
--------------------------------

ARCHITECTURE behavioral OF not_gate IS
BEGIN
   B <= NOT A;
END behavioral;

exercise/model/or_gate.vhdl
LIBRARY ieee;
USE ieee.std_logic_1164.all;
---------------------------------
ENTITY or_gate IS
   PORT (A, B: IN STD_LOGIC_VECTOR(0 TO 1);
   C: OUT STD_LOGIC_VECTOR(0 TO 1));
END or_gate;
--------------------------------

ARCHITECTURE behavioral OF or_gate IS
BEGIN
   C <= A OR B;
END behavioral;

exercise/model/xor_gate.vhdl
LIBRARY ieee;
USE ieee.std_logic_1164.all;
---------------------------------
ENTITY xor_gate IS
   PORT (A, B: IN STD_LOGIC_VECTOR(0 TO 1);
   C: OUT STD_LOGIC_VECTOR(0 TO 1));
END xor_gate;
--------------------------------

ARCHITECTURE behavioral OF xor_gate IS
BEGIN
   C <= A XOR B;
END behavioral;

exercise/runme/and_gate.vhdl
LIBRARY ieee;
USE ieee.std_logic_1164.all;
---------------------------------
ENTITY and_gate IS
   PORT (A, B: IN STD_LOGIC_VECTOR(0 TO 1);
   C: OUT STD_LOGIC_VECTOR(0 TO 1));
END and_gate;
--------------------------------

ARCHITECTURE behavioral OF and_gate IS
BEGIN
   C <= A AND B;
END behavioral;

exercise/runme/alu_2bit.vhdl
LIBRARY ieee;
USE ieee.std_logic_1164.all;
-------------------------
ENTITY alu_2bit is
    port(input_i, input_j: IN STD_LOGIC_VECTOR(0 TO 1);
        operation: IN STD_LOGIC_VECTOR(0 TO 2);
        output_k: OUT STD_LOGIC_VECTOR(0 TO 1);
        c_out: OUT STD_LOGIC
    );
END alu_2bit;
-------------------------
ARCHITECTURE struct of alu_2bit is
    -----ALU COMPONENTS-----
    COMPONENT mux_8to1 is
        PORT(A,B,C,D,E,F,G,H: IN STD_LOGIC_VECTOR(0 TO 1);
        S: IN STD_LOGIC_VECTOR(0 TO 2);
        ALU_RESULT: OUT STD_LOGIC_VECTOR(0 TO 1));
    END COMPONENT;
    COMPONENT and_gate is
        PORT(A,B: IN STD_LOGIC_VECTOR(0 TO 1); C: OUT STD_LOGIC_VECTOR(0 TO 1));
    END COMPONENT;
    COMPONENT or_gate is
        PORT(A,B: IN STD_LOGIC_VECTOR(0 TO 1); C: OUT STD_LOGIC_VECTOR(0 TO 1));
    END COMPONENT;
    COMPONENT xor_gate is
        PORT(A,B: IN STD_LOGIC_VECTOR(0 TO 1); C: OUT STD_LOGIC_VECTOR(0 TO 1));
    END COMPONENT;
    COMPONENT not_gate is
        PORT(A: IN STD_LOGIC_VECTOR(0 TO 1); B: OUT STD_LOGIC_VECTOR(0 TO 1));
    END COMPONENT;
    COMPONENT full_adder_2bit is
        PORT(A, B: IN STD_LOGIC_VECTOR(0 TO 1);
        RESULT:OUT STD_LOGIC_VECTOR(0 TO 1); CARRY_OUT: OUT STD_LOGIC);
    END COMPONENT;
    
    -------LOGICAL OPERATOR OUTPUT WIRES------
    SIGNAL and_signal: STD_LOGIC_VECTOR(0 TO 1);
    SIGNAL xor_signal: STD_LOGIC_VECTOR(0 TO 1);
    SIGNAL or_signal: STD_LOGIC_VECTOR(0 TO 1);
    SIGNAL not_signal: STD_LOGIC_VECTOR(0 TO 1);

    ------ ARITHMETIC OPERATION OUTPUT WIRES ---------
    SIGNAL addition_signal: STD_LOGIC_VECTOR(0 TO 1);
    SIGNAL fs_1s_complement: STD_LOGIC_VECTOR(0 TO 1);
    SIGNAL fs_2s_complement: STD_LOGIC_VECTOR(0 TO 1);
    SIGNAL inc_signal: STD_LOGIC_VECTOR(0 TO 1);
    
    
    --------- HELPER WIRES --------
    SIGNAL fs_subtrahend_complement: STD_LOGIC_VECTOR(0 TO 1);
    SIGNAL fs_borrowOut: STD_LOGIC_VECTOR(0 TO 1) := B"00"; --Borrow wire initialize to 0---
    SIGNAL fs_difference: STD_LOGIC_VECTOR(0 TO 1);
    SIGNAL fs_difference2: STD_LOGIC_VECTOR(0 TO 1);
    SIGNAL noInput: STD_LOGIC_VECTOR(0 TO 1) := B"01"; --ADD ONE TO 2's COMPLEMENT---
    SIGNAL incInput: STD_LOGIC_VECTOR(0 TO 1);


    BEGIN
        incInput <= B"01";
        --AND component--
        and_op: and_gate port map(input_i,input_j,and_signal);
        --XOR component--
        xor_op: xor_gate port map(input_i,input_j,xor_signal);
        --OR component--
        or_op: or_gate port map(input_i,input_j,or_signal);
        --NOT component--
        not_op: not_gate port map(input_i,not_signal);
        --FULL ADDER component--
        fa_2bit_op: full_adder_2bit port map(input_i, input_j, addition_signal, c_out);
        --INCREMENT component--
        increment_op: full_adder_2bit port map(input_i, incInput, inc_signal, c_out);


        --FULL SUBTRACTOR complementer component--
        fs_subtrahend: not_gate port map(input_j, fs_subtrahend_complement);

        --1's complement component--
        fs_2bit_1s_complement: full_adder_2bit port map(input_i, fs_subtrahend_complement, fs_difference, fs_borrowOut(1));
        fs_2bit_1s_complement_with_carry: full_adder_2bit port map(fs_difference, fs_borrowOut, fs_1s_complement, c_out);

        --2's complement component--
        fs_2bit_2s_complement: full_adder_2bit port map(input_i, fs_subtrahend_complement, fs_difference2, fs_borrowOut(1));
        fs_2bit_2s_complement_plus_1: full_adder_2bit port map(fs_difference, noInput, fs_2s_complement, c_out);

        -------- MULTIPLEXER PORTING ----------
        main_mux: mux_8to1 port map(and_signal, or_signal, xor_signal, not_signal, addition_signal, fs_1s_complement, fs_2s_complement, inc_signal, operation, output_k);

END struct;

exercise/runme/alu_2bit_tb.vhd
LIBRARY ieee;
USE ieee.std_logic_1164.all;
ENTITY alu_2bit_tb IS
END alu_2bit_tb;
ARCHITECTURE hardcoded OF alu_2bit_tb IS
   COMPONENT alu_2bit IS
    port(input_i, input_j: IN STD_LOGIC_VECTOR(0 TO 1);
        operation: IN STD_LOGIC_VECTOR(0 TO 2);
        output_k: OUT STD_LOGIC_VECTOR(0 TO 1);
        c_out: OUT STD_LOGIC
    );
   END COMPONENT;
   
   SIGNAL input: STD_LOGIC_VECTOR(0 TO 6);
   SIGNAL res: STD_LOGIC_VECTOR(0 TO 1);
   SIGNAL cout: STD_LOGIC;
BEGIN 
   UUT: alu_2bit PORT MAP (
      operation => input(0 to 2),
      input_i => input(3 to 4),
      input_j => input(5 to 6),
      output_k => res,
      c_out => cout
   );
   STIM_PROC: PROCESS
   BEGIN
      --------- TEST CASES FROM THE EXERCISE HANDOUT -----------
      input <= "0001011"; WAIT FOR 10 NS; ASSERT res="10" REPORT "0001011 failed,res= " & STD_LOGIC'IMAGE(res(0))& STD_LOGIC'IMAGE(res(1));
      input <= "0011011"; WAIT FOR 10 NS; ASSERT res="11" REPORT "0011011 failed,res= " & STD_LOGIC'IMAGE(res(0))& STD_LOGIC'IMAGE(res(1));
      input <= "0101011"; WAIT FOR 10 NS; ASSERT res="01" REPORT "0101011 failed,res= " & STD_LOGIC'IMAGE(res(0))& STD_LOGIC'IMAGE(res(1));
      input <= "0111011"; WAIT FOR 10 NS; ASSERT res="01" REPORT "0111011 failed,res= " & STD_LOGIC'IMAGE(res(0))& STD_LOGIC'IMAGE(res(1));
      input <= "1001011"; WAIT FOR 10 NS; ASSERT res="01" REPORT "1001011 failed,res= " & STD_LOGIC'IMAGE(res(0))& STD_LOGIC'IMAGE(res(1));
      input <= "1011011"; WAIT FOR 10 NS; ASSERT res="10" REPORT "1011011 failed,res= " & STD_LOGIC'IMAGE(res(0))& STD_LOGIC'IMAGE(res(1));
      input <= "1101011"; WAIT FOR 10 NS; ASSERT res="11" REPORT "1101011 failed,res= " & STD_LOGIC'IMAGE(res(0))& STD_LOGIC'IMAGE(res(1));
      input <= "1111011"; WAIT FOR 10 NS; ASSERT res="11" REPORT "1111011 failed,res= " & STD_LOGIC'IMAGE(res(0))& STD_LOGIC'IMAGE(res(1));
      WAIT;
   END PROCESS;
END;

exercise/alu_2bit.vcd
$date
  Sun Oct  4 11:26:55 2020
$end
$version
  GHDL v0
$end
$timescale
  1 fs
$end
$scope module standard $end
$upscope $end
$scope module std_logic_1164 $end
$upscope $end
$scope module numeric_std $end
$upscope $end
$scope module alu_2bit_tb $end
$var reg 7 ! input[0:6] $end
$var reg 2 " res[0:1] $end
$var reg 1 # cout $end
$scope module uut $end
$var reg 2 $ input_i[0:1] $end
$var reg 2 % input_j[0:1] $end
$var reg 3 & operation[0:2] $end
$var reg 2 ' output_k[0:1] $end
$var reg 1 ( c_out $end
$var reg 2 ) and_signal[0:1] $end
$var reg 2 * xor_signal[0:1] $end
$var reg 2 + or_signal[0:1] $end
$var reg 2 , not_signal[0:1] $end
$var reg 2 - addition_signal[0:1] $end
$var reg 2 . fs_1s_complement[0:1] $end
$var reg 2 / fs_2s_complement[0:1] $end
$var reg 2 0 inc_signal[0:1] $end
$var reg 2 1 fs_subtrahend_complement[0:1] $end
$var reg 2 2 fs_borrowout[0:1] $end
$var reg 2 3 fs_difference[0:1] $end
$var reg 2 4 fs_difference2[0:1] $end
$var reg 2 5 noinput[0:1] $end
$var reg 2 6 incinput[0:1] $end
$scope module and_op $end
$var reg 2 7 a[0:1] $end
$var reg 2 8 b[0:1] $end
$var reg 2 9 c[0:1] $end
$upscope $end
$scope module xor_op $end
$var reg 2 : a[0:1] $end
$var reg 2 ; b[0:1] $end
$var reg 2 < c[0:1] $end
$upscope $end
$scope module or_op $end
$var reg 2 = a[0:1] $end
$var reg 2 > b[0:1] $end
$var reg 2 ? c[0:1] $end
$upscope $end
$scope module not_op $end
$var reg 2 @ a[0:1] $end
$var reg 2 A b[0:1] $end
$upscope $end
$scope module fa_2bit_op $end
$var reg 2 B a[0:1] $end
$var reg 2 C b[0:1] $end
$var reg 2 D result[0:1] $end
$var reg 1 E carry_out $end
$var reg 1 F carryout1 $end
$var reg 1 G noinput $end
$scope module full_adder2 $end
$var reg 1 H a $end
$var reg 1 I b $end
$var reg 1 J carryin $end
$var reg 1 K sum $end
$var reg 1 L carryout $end
$upscope $end
$scope module full_adder1 $end
$var reg 1 M a $end
$var reg 1 N b $end
$var reg 1 O carryin $end
$var reg 1 P sum $end
$var reg 1 Q carryout $end
$upscope $end
$upscope $end
$scope module increment_op $end
$var reg 2 R a[0:1] $end
$var reg 2 S b[0:1] $end
$var reg 2 T result[0:1] $end
$var reg 1 U carry_out $end
$var reg 1 V carryout1 $end
$var reg 1 W noinput $end
$scope module full_adder2 $end
$var reg 1 X a $end
$var reg 1 Y b $end
$var reg 1 Z carryin $end
$var reg 1 [ sum $end
$var reg 1 \ carryout $end
$upscope $end
$scope module full_adder1 $end
$var reg 1 ] a $end
$var reg 1 ^ b $end
$var reg 1 _ carryin $end
$var reg 1 ` sum $end
$var reg 1 a carryout $end
$upscope $end
$upscope $end
$scope module fs_subtrahend $end
$var reg 2 b a[0:1] $end
$var reg 2 c b[0:1] $end
$upscope $end
$scope module fs_2bit_1s_complement $end
$var reg 2 d a[0:1] $end
$var reg 2 e b[0:1] $end
$var reg 2 f result[0:1] $end
$var reg 1 g carry_out $end
$var reg 1 h carryout1 $end
$var reg 1 i noinput $end
$scope module full_adder2 $end
$var reg 1 j a $end
$var reg 1 k b $end
$var reg 1 l carryin $end
$var reg 1 m sum $end
$var reg 1 n carryout $end
$upscope $end
$scope module full_adder1 $end
$var reg 1 o a $end
$var reg 1 p b $end
$var reg 1 q carryin $end
$var reg 1 r sum $end
$var reg 1 s carryout $end
$upscope $end
$upscope $end
$scope module fs_2bit_1s_complement_with_carry $end
$var reg 2 t a[0:1] $end
$var reg 2 u b[0:1] $end
$var reg 2 v result[0:1] $end
$var reg 1 w carry_out $end
$var reg 1 x carryout1 $end
$var reg 1 y noinput $end
$scope module full_adder2 $end
$var reg 1 z a $end
$var reg 1 { b $end
$var reg 1 | carryin $end
$var reg 1 } sum $end
$var reg 1 !" carryout $end
$upscope $end
$scope module full_adder1 $end
$var reg 1 "" a $end
$var reg 1 #" b $end
$var reg 1 $" carryin $end
$var reg 1 %" sum $end
$var reg 1 &" carryout $end
$upscope $end
$upscope $end
$scope module fs_2bit_2s_complement $end
$var reg 2 '" a[0:1] $end
$var reg 2 (" b[0:1] $end
$var reg 2 )" result[0:1] $end
$var reg 1 *" carry_out $end
$var reg 1 +" carryout1 $end
$var reg 1 ," noinput $end
$scope module full_adder2 $end
$var reg 1 -" a $end
$var reg 1 ." b $end
$var reg 1 /" carryin $end
$var reg 1 0" sum $end
$var reg 1 1" carryout $end
$upscope $end
$scope module full_adder1 $end
$var reg 1 2" a $end
$var reg 1 3" b $end
$var reg 1 4" carryin $end
$var reg 1 5" sum $end
$var reg 1 6" carryout $end
$upscope $end
$upscope $end
$scope module fs_2bit_2s_complement_plus_1 $end
$var reg 2 7" a[0:1] $end
$var reg 2 8" b[0:1] $end
$var reg 2 9" result[0:1] $end
$var reg 1 :" carry_out $end
$var reg 1 ;" carryout1 $end
$var reg 1 <" noinput $end
$scope module full_adder2 $end
$var reg 1 =" a $end
$var reg 1 >" b $end
$var reg 1 ?" carryin $end
$var reg 1 @" sum $end
$var reg 1 A" carryout $end
$upscope $end
$scope module full_adder1 $end
$var reg 1 B" a $end
$var reg 1 C" b $end
$var reg 1 D" carryin $end
$var reg 1 E" sum $end
$var reg 1 F" carryout $end
$upscope $end
$upscope $end
$scope module main_mux $end
$var reg 2 G" a[0:1] $end
$var reg 2 H" b[0:1] $end
$var reg 2 I" c[0:1] $end
$var reg 2 J" d[0:1] $end
$var reg 2 K" e[0:1] $end
$var reg 2 L" f[0:1] $end
$var reg 2 M" g[0:1] $end
$var reg 2 N" h[0:1] $end
$var reg 3 O" s[0:2] $end
$var reg 2 P" alu_result[0:1] $end
$upscope $end
$upscope $end
$upscope $end
$enddefinitions $end
#0
b0001011 !
b10 "
X#
b10 $
b11 %
b000 &
b10 '
X(
b10 )
b01 *
b11 +
b01 ,
b01 -
b10 .
b11 /
b11 0
b00 1
b00 2
b10 3
b10 4
b01 5
b01 6
b10 7
b11 8
b10 9
b10 :
b11 ;
b01 <
b10 =
b11 >
b11 ?
b10 @
b01 A
b10 B
b11 C
b01 D
XE
0F
0G
0H
1I
0J
1K
0L
1M
1N
0O
0P
XQ
b10 R
b01 S
b11 T
XU
0V
0W
0X
1Y
0Z
1[
0\
1]
0^
0_
1`
Xa
b11 b
b00 c
b10 d
b00 e
b10 f
0g
0h
0i
0j
0k
0l
0m
0n
1o
0p
0q
1r
0s
b10 t
b00 u
b10 v
Xw
0x
0y
0z
0{
0|
0}
0!"
1""
0#"
0$"
1%"
X&"
b10 '"
b00 ("
b10 )"
0*"
0+"
0,"
0-"
0."
0/"
00"
01"
12"
03"
04"
15"
06"
b10 7"
b01 8"
b11 9"
X:"
0;"
0<"
0="
1>"
0?"
1@"
0A"
1B"
0C"
0D"
1E"
XF"
b10 G"
b11 H"
b01 I"
b01 J"
b01 K"
b10 L"
b11 M"
b11 N"
b000 O"
b10 P"
#10000000
b0011011 !
b11 "
b001 &
b11 '
b001 O"
b11 P"
#20000000
b0101011 !
b01 "
b010 &
b01 '
b010 O"
b01 P"
#30000000
b0111011 !
b011 &
b011 O"
#40000000
b1001011 !
b100 &
b100 O"
#50000000
b1011011 !
b10 "
b101 &
b10 '
b101 O"
b10 P"
#60000000
b1101011 !
b11 "
b110 &
b11 '
b110 O"
b11 P"
#70000000
b1111011 !
b111 &
b111 O"
